elfdeps/__init__.py
elfdeps/__main__.py
elfdeps/_archives.py
elfdeps/_elfdeps.py
elfdeps/_fileinfo.py
elfdeps/py.typed
elfdeps-0.2.0.dist-info/LICENSE
elfdeps-0.2.0.dist-info/METADATA
elfdeps-0.2.0.dist-info/WHEEL
elfdeps-0.2.0.dist-info/entry_points.txt
elfdeps-0.2.0.dist-info/top_level.txt
elfdeps-0.2.0.dist-info/RECORD
